paytext/__init__.py
paytext/paytext.py
paytext-0.0.2.dist-info/METADATA
paytext-0.0.2.dist-info/RECORD
paytext-0.0.2.dist-info/WHEEL
paytext-0.0.2.dist-info/top_level.txt
tests/__init__.py
tests/paytext_test.py
tests/pyre_strict_test.py
