Metadata-Version: 2.1
Name: paytext
Version: 0.0.2
Summary: Generalize texts from payment card transactions
Home-page: https://github.com/yhoiseth/paytext
Author: Yngve Høiseth
Author-email: yngve@hoiseth.net
License: UNKNOWN
Platform: UNKNOWN
Classifier: Programming Language :: Python :: 3
Classifier: License :: OSI Approved :: MIT License
Classifier: Operating System :: OS Independent
